.travis.yml
MANIFEST.in
README.rst
manage.py
runtests.py
setup.cfg
setup.py
tox.ini
django_yamoney.egg-info/PKG-INFO
django_yamoney.egg-info/SOURCES.txt
django_yamoney.egg-info/dependency_links.txt
django_yamoney.egg-info/requires.txt
django_yamoney.egg-info/top_level.txt
tests/__init__.py
tests/test_settings.py
tests/urls.py
yamoney/__init__.py
yamoney/admin.py
yamoney/apps.py
yamoney/conf.py
yamoney/fields.py
yamoney/forms.py
yamoney/models.py
yamoney/signals.py
yamoney/tests.py
yamoney/urls.py
yamoney/views.py
yamoney/widgets.py
yamoney/migrations/0001_initial.py
yamoney/migrations/0002_auto_20170411_0731.py
yamoney/migrations/__init__.py